{"namedChunkGroups":{"polyfill":{"name":"polyfill","assets":[{"name":"webpack-runtime-d60795857070567795db.js","size":3776},{"name":"polyfill-0d600ac9c5f7277ff7fd.js","size":82635}],"filteredAssets":0,"assetsSize":86411,"filteredAuxiliaryAssets":2,"auxiliaryAssetsSize":216918},"app":{"name":"app","assets":[{"name":"webpack-runtime-d60795857070567795db.js","size":3776},{"name":"framework-0228706ac3bf5a0a6c64.js","size":130485},{"name":"styles.e8344dd60b1388b2f734.css","size":7416},{"name":"app-dd2a9a7e67aec236ec9e.js","size":65033}],"filteredAssets":0,"assetsSize":206710,"filteredAuxiliaryAssets":3,"auxiliaryAssetsSize":630902},"component---src-pages-index-js":{"name":"component---src-pages-index-js","assets":[{"name":"framework-0228706ac3bf5a0a6c64.js","size":130485},{"name":"component---src-pages-index-js-da5d040daa62de5022b1.js","size":240257}],"filteredAssets":0,"assetsSize":370742,"filteredAuxiliaryAssets":2,"auxiliaryAssetsSize":1478048}},"assetsByChunkName":{"polyfill":["webpack-runtime-d60795857070567795db.js","polyfill-0d600ac9c5f7277ff7fd.js"],"app":["webpack-runtime-d60795857070567795db.js","framework-0228706ac3bf5a0a6c64.js","styles.e8344dd60b1388b2f734.css","app-dd2a9a7e67aec236ec9e.js"],"component---src-pages-index-js":["framework-0228706ac3bf5a0a6c64.js","component---src-pages-index-js-da5d040daa62de5022b1.js"]},"childAssetsByChunkName":{}}